bammix/__init__.py
bammix/bammix_functions.py
bammix/command.py
bammix-1.0.0.dist-info/LICENSE
bammix-1.0.0.dist-info/METADATA
bammix-1.0.0.dist-info/WHEEL
bammix-1.0.0.dist-info/entry_points.txt
bammix-1.0.0.dist-info/top_level.txt
bammix-1.0.0.dist-info/RECORD
