Metadata-Version: 2.1
Name: bammix
Version: 1.0.0
Summary: bammix
Home-page: https://github.com/chrisruis/bammix
Author: Chris Ruis
Author-email: cr628@cam.ac.uk
License: UNKNOWN
Platform: UNKNOWN
Classifier: Programming Language :: Python :: 3
Classifier: License :: OSI Approved :: MIT License
Classifier: Operating System :: OS Independent
Requires-Python: >=3.6.0
License-File: LICENSE
Requires-Dist: pysam (>=0.17.0)
Requires-Dist: matplotlib (>=3.2.1)
